{"chunk_definitions":[{"row":55,"row_count":1,"visible":true,"expansion_state":0,"options":{"engine":"r","label":"setup","include":false},"document_id":"6E95DE79","chunk_id":"csetup_chunk","chunk_label":"setup"},{"row":66,"row_count":1,"visible":true,"expansion_state":0,"options":{"engine":"r","label":"unnamed-chunk-1"},"document_id":"6E95DE79","chunk_id":"cp9ugbv30h3pz","chunk_label":"unnamed-chunk-1"},{"row":77,"row_count":1,"visible":true,"expansion_state":0,"options":{"engine":"r","label":"unnamed-chunk-2"},"document_id":"6E95DE79","chunk_id":"cbgyo1t0fqpgm","chunk_label":"unnamed-chunk-2"},{"row":108,"row_count":1,"visible":true,"expansion_state":0,"options":{"engine":"r","label":"unnamed-chunk-3"},"document_id":"6E95DE79","chunk_id":"c6awpkrviwvax","chunk_label":"unnamed-chunk-3"},{"row":231,"row_count":1,"visible":true,"expansion_state":0,"options":{"engine":"r","label":"unnamed-chunk-214"},"document_id":"6E95DE79","chunk_id":"c3cfoeps2uf36","chunk_label":"unnamed-chunk-4"},{"row":264,"row_count":1,"visible":true,"expansion_state":0,"options":{"engine":"r","warning":false,"label":"unnamed-chunk-216"},"document_id":"6E95DE79","chunk_id":"cu8acbqunkeyz","chunk_label":"unnamed-chunk-5"},{"row":282,"row_count":1,"visible":true,"expansion_state":0,"options":{"engine":"r","label":"unnamed-chunk-217"},"document_id":"6E95DE79","chunk_id":"cfe3uh8kyywpj","chunk_label":"unnamed-chunk-6"},{"row":291,"row_count":1,"visible":true,"expansion_state":0,"options":{"engine":"r","label":"unnamed-chunk-218"},"document_id":"6E95DE79","chunk_id":"czl5lgwi08ns9","chunk_label":"unnamed-chunk-7"},{"row":355,"row_count":1,"visible":true,"expansion_state":0,"options":{"engine":"r","label":"unnamed-chunk-219"},"document_id":"6E95DE79","chunk_id":"cg0cleqah8jel","chunk_label":"unnamed-chunk-8"},{"row":410,"row_count":1,"visible":true,"expansion_state":0,"options":{"engine":"r","label":"unnamed-chunk-220"},"document_id":"6E95DE79","chunk_id":"cjrucbw4xkcqd","chunk_label":"unnamed-chunk-9"}],"doc_write_time":1688545228,"working_dir":null,"default_chunk_options":{"echo":true,"fig.width":9.0,"message":false,"warning":false}}